tests/__init__.py
tests/benchmark_models.py
tests/conftest.py
tests/endpoint.py
tests/run_tests.py
tests/test_agent.py
tests/test_agent_fallback_memory.py
tests/test_agent_memory_consistency.py
tests/test_agent_type.py
tests/test_api_endpoint.py
tests/test_bedrock.py
tests/test_fallback.py
tests/test_gemini.py
tests/test_groq.py
tests/test_openai.py
tests/test_private_llm.py
tests/test_react_error_handling.py
tests/test_react_memory.py
tests/test_react_streaming.py
tests/test_react_workflow_events.py
tests/test_return_direct.py
tests/test_serialization.py
tests/test_session_memory.py
tests/test_streaming.py
tests/test_together.py
tests/test_tools.py
tests/test_vectara_llms.py
tests/test_vhc.py
tests/test_workflow.py
vectara_agentic/__init__.py
vectara_agentic/_callback.py
vectara_agentic/_observability.py
vectara_agentic/_version.py
vectara_agentic/agent.py
vectara_agentic/agent_config.py
vectara_agentic/agent_endpoint.py
vectara_agentic/db_tools.py
vectara_agentic/llm_utils.py
vectara_agentic/sub_query_workflow.py
vectara_agentic/tool_utils.py
vectara_agentic/tools.py
vectara_agentic/tools_catalog.py
vectara_agentic/types.py
vectara_agentic/utils.py
vectara_agentic/agent_core/__init__.py
vectara_agentic/agent_core/factory.py
vectara_agentic/agent_core/prompts.py
vectara_agentic/agent_core/serialization.py
vectara_agentic/agent_core/streaming.py
vectara_agentic/agent_core/utils/__init__.py
vectara_agentic/agent_core/utils/hallucination.py
vectara_agentic/agent_core/utils/logging.py
vectara_agentic/agent_core/utils/schemas.py
vectara_agentic/agent_core/utils/tools.py
vectara_agentic-0.4.10.dist-info/licenses/LICENSE
vectara_agentic-0.4.10.dist-info/METADATA
vectara_agentic-0.4.10.dist-info/WHEEL
vectara_agentic-0.4.10.dist-info/top_level.txt
vectara_agentic-0.4.10.dist-info/RECORD
