Metadata-Version: 2.4
Name: vectara_agentic
Version: 0.4.10
Summary: A Python package for creating AI Assistants and AI Agents with Vectara
Home-page: https://github.com/vectara/py-vectara-agentic
Author: Ofer Mendelevitch
Author-email: ofer@vectara.com
Project-URL: Documentation, https://vectara.github.io/py-vectara-agentic/
Keywords: LLM,NLP,RAG,Agentic-RAG,AI assistant,AI Agent,Vectara
Classifier: Programming Language :: Python :: 3
Classifier: License :: OSI Approved :: Apache Software License
Classifier: Operating System :: OS Independent
Classifier: Development Status :: 4 - Beta
Classifier: Topic :: Scientific/Engineering :: Artificial Intelligence
Classifier: Topic :: Software Development :: Libraries :: Python Modules
Requires-Python: >=3.10
License-File: LICENSE
Requires-Dist: llama-index==0.14.7
Requires-Dist: llama-index-core==0.14.7
Requires-Dist: llama-index-workflows==2.10.3
Requires-Dist: llama-index-cli==0.5.3
Requires-Dist: llama-index-indices-managed-vectara==0.5.1
Requires-Dist: llama-index-llms-openai==0.6.7
Requires-Dist: llama-index-llms-openai-like==0.5.3
Requires-Dist: llama-index-llms-anthropic==0.9.7
Requires-Dist: llama-index-llms-together==0.4.1
Requires-Dist: llama-index-llms-groq==0.4.1
Requires-Dist: llama-index-llms-cohere==0.6.1
Requires-Dist: llama-index-llms-google-genai==0.7.1
Requires-Dist: google_genai==1.48.0
Requires-Dist: llama-index-llms-bedrock-converse==0.11.0
Requires-Dist: llama-index-tools-yahoo-finance==0.4.1
Requires-Dist: llama-index-tools-arxiv==0.4.1
Requires-Dist: llama-index-tools-database==0.4.1
Requires-Dist: llama-index-tools-google==0.6.2
Requires-Dist: llama-index-tools-tavily_research==0.4.1
Requires-Dist: llama_index.tools.brave_search==0.4.1
Requires-Dist: llama-index-tools-neo4j==0.4.1
Requires-Dist: llama-index-tools-waii==0.4.1
Requires-Dist: llama-index-graph-stores-kuzu==0.9.1
Requires-Dist: llama-index-tools-salesforce==0.4.1
Requires-Dist: llama-index-tools-slack==0.4.1
Requires-Dist: llama-index-tools-exa==0.4.1
Requires-Dist: llama-index-tools-wikipedia==0.4.1
Requires-Dist: llama-index-tools-bing-search==0.4.1
Requires-Dist: openai>=1.99.3
Requires-Dist: tavily-python>=0.7.10
Requires-Dist: exa-py>=1.14.20
Requires-Dist: openinference-instrumentation-llama-index==4.3.8
Requires-Dist: opentelemetry-proto>=1.31.0
Requires-Dist: arize-phoenix==12.9.0
Requires-Dist: arize-phoenix-otel==0.13.1
Requires-Dist: arize-phoenix-client==1.21.0
Requires-Dist: arize-phoenix-evals==2.5.0
Requires-Dist: protobuf==5.29.5
Requires-Dist: tokenizers>=0.20
Requires-Dist: pydantic>=2.11.5
Requires-Dist: pandas==2.2.3
Requires-Dist: retrying==1.4.2
Requires-Dist: python-dotenv==1.0.1
Requires-Dist: cloudpickle>=3.1.1
Requires-Dist: httpx==0.28.1
Requires-Dist: commonmark==0.9.1
Dynamic: author
Dynamic: author-email
Dynamic: classifier
Dynamic: description
Dynamic: description-content-type
Dynamic: home-page
Dynamic: keywords
Dynamic: license-file
Dynamic: project-url
Dynamic: requires-dist
Dynamic: requires-python
Dynamic: summary
